{
  "metaData": {
    "title": "Velora | Empowering Elegance: Uniting Design & Flexibility",
    "description": "Velora is a versatile front-end framework combining the power of Bulma and Tailwind CSS, providing an elegant and efficient solution for modern web development.",
    "author": "Mikko",
    "keywords": [
      "Velora",
      "Bulma",
      "Tailwind CSS",
      "frontend",
      "framework",
      "web development",
      "responsive design",
      "UI components"
    ],
    "ogImage": "https://velora.site/public/images/ogimage.jpg"
  },
  "baseURL": "https://velora.site",
  "logo": "/images/logo.png",
  "logo_light": "/images/logo-light.png",
  "logoText": "Velora",
  "favicon": "/images/bulma_ico_png.png",
  "postPerPage": 6,
  "postColumns": 2,
  "copyright": "© 2023 Velora. All rights reserved."
}